odoo/addons/pattern_import_export_csv/README.rst
odoo/addons/pattern_import_export_csv/__init__.py
odoo/addons/pattern_import_export_csv/__manifest__.py
odoo/addons/pattern_import_export_csv/demo/demo.xml
odoo/addons/pattern_import_export_csv/migrations/12.0.2.0.0/post-migrate.py
odoo/addons/pattern_import_export_csv/models/__init__.py
odoo/addons/pattern_import_export_csv/models/pattern_config.py
odoo/addons/pattern_import_export_csv/models/pattern_file.py
odoo/addons/pattern_import_export_csv/readme/CONFIGURE.rst
odoo/addons/pattern_import_export_csv/readme/CONTRIBUTORS.rst
odoo/addons/pattern_import_export_csv/readme/DESCRIPTION.rst
odoo/addons/pattern_import_export_csv/readme/USAGE.rst
odoo/addons/pattern_import_export_csv/static/description/index.html
odoo/addons/pattern_import_export_csv/tests/__init__.py
odoo/addons/pattern_import_export_csv/tests/common.py
odoo/addons/pattern_import_export_csv/tests/test_pattern_export.py
odoo/addons/pattern_import_export_csv/tests/test_pattern_import.py
odoo/addons/pattern_import_export_csv/tests/fixtures/example.partners.failed.csv
odoo/addons/pattern_import_export_csv/tests/fixtures/example.partners.ok.csv
odoo/addons/pattern_import_export_csv/tests/fixtures/example.partners.parent.csv
odoo/addons/pattern_import_export_csv/tests/fixtures/example.users.descriptive.ok.csv
odoo/addons/pattern_import_export_csv/tests/fixtures/example.users.failed.csv
odoo/addons/pattern_import_export_csv/tests/fixtures/example.users.ok.csv
odoo/addons/pattern_import_export_csv/tests/fixtures/example.users.ok.fmt2.csv
odoo/addons/pattern_import_export_csv/views/pattern_config.xml
odoo12_addon_pattern_import_export_csv-12.0.4.0.0.dist-info/METADATA
odoo12_addon_pattern_import_export_csv-12.0.4.0.0.dist-info/WHEEL
odoo12_addon_pattern_import_export_csv-12.0.4.0.0.dist-info/top_level.txt
odoo12_addon_pattern_import_export_csv-12.0.4.0.0.dist-info/RECORD
