Metadata-Version: 2.1
Name: odoo12-addon-pattern-import-export-csv
Version: 12.0.4.0.0
Summary: Pattern for import or export from to CSV files
Home-page: https://github.com/OCA/pattern-import-export
Author: Akretion, Odoo Community Association (OCA)
Author-email: support@odoo-community.org
License: AGPL-3
Platform: UNKNOWN
Classifier: Programming Language :: Python
Classifier: Framework :: Odoo
Classifier: License :: OSI Approved :: GNU Affero General Public License v3
Requires-Python: >=3.5
Requires-Dist: odoo12-addon-pattern-import-export
Requires-Dist: odoo (<12.1dev,>=12.0a)
